examples/minimize_J.py
integor/__init__.py
integor/main.py
integor/pseudo_func.py
test/test_operations.py
integor-1.2.dist-info/METADATA
integor-1.2.dist-info/WHEEL
integor-1.2.dist-info/top_level.txt
integor-1.2.dist-info/RECORD
