Metadata-Version: 2.1
Name: integor
Version: 1.2
Summary: Optimization and constraint satisfaction for integer linear programs in a user-friendly way
Home-page: https://github.com/tboulet/IntegOR
Author: Timothé Boulet
Author-email: timothe.boulet0@gmail.com
License: MIT
